add.v
module add    //不同符号的浮点数据相加
(
	input wire MAIN_CLK,    
	input wire [31:0] a,
	input wire [31:0] b,
	
	output wire [31:0] ab
);
 
reg [7:0] pow_a;
reg [7:0] pow_b;
reg [22:0] val_a;
reg [22:0] val_b;
reg flag_a;
reg flag_b;
reg flag;

//比较指数大小提取指数差值
reg [24:0] val_max;
reg [24:0] val_min; 
reg [7:0] pow_diff;
reg [7:0] pow_ab1;
reg flag1;

//计数输出时的数值部分
reg [7:0] pow_ab2;
reg [24:0] val_ab1;
reg flag2;

//对最后的输出指数部分和数据部分进行校准
reg [8:0] pow_ab3;
reg [23:0] val_ab2;
reg flag3;


always @(MAIN_CLK )
begin

	flag_a = a[31];   //提取符号
	flag_b= b[31];
	flag = flag_a^flag_b;
	pow_a = a[30:23];
	pow_b = b[30:23];
	val_a = a[22:0];
	val_b = b[22:0];
	if (flag ) begin 
		if(pow_a > pow_b)    
		begin
			flag1 = flag_a;  //输出符号随a
			pow_ab1 = pow_a;
			pow_diff = pow_a - pow_b;
			val_max = {2'b01,val_a};
			val_min = {2'b01,val_b};
		end
	else if(pow_a < pow_b) 
		begin
			flag1 = flag_b;  //输出符号随b
			pow_ab1 = pow_b;
			pow_diff = pow_b - pow_a;
			val_max = {2'b01,val_b};
			val_min = {2'b01,val_a};
		end
	else
		begin
			pow_ab1 = pow_a;
			pow_diff = 0;
			if(val_a > val_b)
				begin
					flag1 = flag_a;  //输出符号随a
					val_max = {2'b01,val_a};
					val_min = {2'b01,val_b};
				end
			else //if(val_a < val_b)
				begin
					flag1 = flag_b;  //输出符号随b
					val_max = {2'b01,val_b};
					val_min = {2'b01,val_a};
				end 
		end 
	end
	
	else begin
		flag1 = flag_a;
	if(pow_a > pow_b)    
		begin
			pow_ab1 = pow_a;
			pow_diff = pow_a - pow_b;
			val_max = {2'b01,val_a};
			val_min = {2'b01,val_b};
		end
	else 
		begin
			pow_ab1 = pow_b;
			pow_diff = pow_b - pow_a;
			val_max = {2'b01,val_b};
			val_min = {2'b01,val_a};
		end
	
	end
	
		flag2 = flag1;
	pow_ab2 = pow_ab1;
	if (flag) begin
	case(pow_diff)
		0: begin val_ab1 = val_max - val_min; end
		1: begin val_ab1 = val_max - {1'b0,val_min[24:1]}; end
		2: begin val_ab1 = val_max - {2'b0,val_min[24:2]}; end
		3: begin val_ab1 = val_max - {3'b0,val_min[24:3]}; end
		4: begin val_ab1 = val_max - {4'b0,val_min[24:4]}; end
		5: begin val_ab1 = val_max - {5'b0,val_min[24:5]}; end
		6: begin val_ab1 = val_max - {6'b0,val_min[24:6]}; end
		7: begin val_ab1 = val_max - {7'b0,val_min[24:7]}; end
		8: begin val_ab1 = val_max - {8'b0,val_min[24:8]}; end
		9: begin val_ab1 = val_max - {9'b0,val_min[24:9]}; end
		10: begin val_ab1 = val_max - {10'b0,val_min[24:10]}; end
		11: begin val_ab1 = val_max - {11'b0,val_min[24:11]}; end
		12: begin val_ab1 = val_max - {12'b0,val_min[24:12]}; end
		13: begin val_ab1 = val_max - {13'b0,val_min[24:13]}; end
		14: begin val_ab1 = val_max - {14'b0,val_min[24:14]}; end
//		15: begin val_ab1 <= val_max - {15'b0,val_min[24:15]}; end
//		16: begin val_ab1 <= val_max - {16'b0,val_min[24:16]}; end
//		17: begin val_ab1 <= val_max - {17'b0,val_min[24:17]}; end
//		18: begin val_ab1 <= val_max - {18'b0,val_min[24:18]}; end
//		19: begin val_ab1 <= val_max - {19'b0,val_min[24:19]}; end
//		20: begin val_ab1 <= val_max - {20'b0,val_min[24:20]}; end
//		21: begin val_ab1 <= val_max - {21'b0,val_min[24:21]}; end
//		22: begin val_ab1 <= val_max - {22'b0,val_min[24:22]}; end
//		23: begin val_ab1 <= val_max - {23'b0,val_min[24:23]}; end
		default: begin val_ab1 = val_max; end
	endcase 
	end
	else begin
	case(pow_diff)
		0: begin val_ab1 = val_max + val_min; end
		1: begin val_ab1 = val_max + {1'b0,val_min[24:1]}; end
		2: begin val_ab1 = val_max + {2'b0,val_min[24:2]}; end
		3: begin val_ab1 = val_max + {3'b0,val_min[24:3]}; end
		4: begin val_ab1 = val_max + {4'b0,val_min[24:4]}; end
		5: begin val_ab1 = val_max + {5'b0,val_min[24:5]}; end
		6: begin val_ab1 = val_max + {6'b0,val_min[24:6]}; end
		7: begin val_ab1 = val_max + {7'b0,val_min[24:7]}; end
		8: begin val_ab1 = val_max + {8'b0,val_min[24:8]}; end
		9: begin val_ab1 = val_max + {9'b0,val_min[24:9]}; end
		10: begin val_ab1 = val_max + {10'b0,val_min[24:10]}; end
		11: begin val_ab1 = val_max + {11'b0,val_min[24:11]}; end
		12: begin val_ab1 = val_max + {12'b0,val_min[24:12]}; end
		13: begin val_ab1 = val_max + {13'b0,val_min[24:13]}; end
		14: begin val_ab1 = val_max + {14'b0,val_min[24:14]}; end
//		15: begin val_ab1 <= val_max + {15'b0,val_min[24:15]}; end
//		16: begin val_ab1 <= val_max + {16'b0,val_min[24:16]}; end
//		17: begin val_ab1 <= val_max + {17'b0,val_min[24:17]}; end
//		18: begin val_ab1 <= val_max + {18'b0,val_min[24:18]}; end
//		19: begin val_ab1 <= val_max + {19'b0,val_min[24:19]}; end
//		20: begin val_ab1 <= val_max + {20'b0,val_min[24:20]}; end
//		21: begin val_ab1 <= val_max + {21'b0,val_min[24:21]}; end
//		22: begin val_ab1 <= val_max + {22'b0,val_min[24:22]}; end
//		23: begin val_ab1 <= val_max + {23'b0,val_min[24:23]}; end
		default: begin val_ab1 = val_max; end
	endcase 
	end
	
	if (flag) begin 
	flag3 = flag2;
	if(val_ab1[23] == 1)   //说明减法过程中数据没有借位
		begin
			pow_ab3 = pow_ab2;
			val_ab2 = val_ab1[23:0]; //得到最后输出的小数部分
		end
	else if(val_ab1[22] == 1)
		begin
			pow_ab3 = pow_ab2 - 1;
			val_ab2 = {val_ab1[22:0],1'b0}; //得到最后输出的小数部分			
		end
	else if(val_ab1[21] == 1)
		begin
			pow_ab3 = pow_ab2 - 2;
			val_ab2 = {val_ab1[21:0],2'b0}; //得到最后输出的小数部分			
		end
	else if(val_ab1[20] == 1)
		begin
			pow_ab3 = pow_ab2 - 3;
			val_ab2 = {val_ab1[20:0],3'b0}; //得到最后输出的小数部分			
		end
	else if(val_ab1[19] == 1)
		begin
			pow_ab3 = pow_ab2 - 4;
			val_ab2 = {val_ab1[19:0],4'b0}; //得到最后输出的小数部分			
		end
	else if(val_ab1[18] == 1)
		begin
			pow_ab3 = pow_ab2 - 5;
			val_ab2 = {val_ab1[18:0],5'b0}; //得到最后输出的小数部分			
		end
	else if(val_ab1[17] == 1)
		begin
			pow_ab3 = pow_ab2 - 6;
			val_ab2 = {val_ab1[17:0],6'b0}; //得到最后输出的小数部分			
		end
	else if(val_ab1[16] == 1)
		begin
			pow_ab3 = pow_ab2 - 7;
			val_ab2 = {val_ab1[16:0],7'b0}; //得到最后输出的小数部分			
		end
	else if(val_ab1[15] == 1)
		begin
			pow_ab3 = pow_ab2 - 8;
			val_ab2 = {val_ab1[15:0],8'b0}; //得到最后输出的小数部分			
		end
	else if(val_ab1[14] == 1)
		begin
			pow_ab3 = pow_ab2 - 9;
			val_ab2 = {val_ab1[14:0],9'b0}; //得到最后输出的小数部分			
		end
	else if(val_ab1[13] == 1)
		begin
			pow_ab3 = pow_ab2 - 10;
			val_ab2 = {val_ab1[13:0],10'b0}; //得到最后输出的小数部分			
		end
	else if(val_ab1[12] == 1)
		begin
			pow_ab3 = pow_ab2 - 11;
			val_ab2 = {val_ab1[12:0],11'b0}; //得到最后输出的小数部分			
		end
	else if(val_ab1[11] == 1)
		begin
			pow_ab3 = pow_ab2 - 12;
			val_ab2 = {val_ab1[11:0],12'b0}; //得到最后输出的小数部分			
		end
	else if(val_ab1[10] == 1)
		begin
			pow_ab3 = pow_ab2 - 13;
			val_ab2 = {val_ab1[10:0],13'b0}; //得到最后输出的小数部分			
		end		
	else
		begin
			pow_ab3 = 0;
			val_ab2 = 0;  
		end 
	end
	
	else begin
	flag3 = flag2;
	if(val_ab1[24] == 1)   //说明加法过程中数据有溢出
		begin
			pow_ab3 = pow_ab2 + 1;
			val_ab2 = val_ab1[24:1]; //得到最后输出的小数部分
		end
	else
		begin
			pow_ab3 = pow_ab2;
			val_ab2 = val_ab1[23:0]; //得到最后输出的小数部分
		end 
	end
	

end

//对输出进行打包 
assign ab = flag ?(pow_ab3[8]==1)?{32'h0}:{flag3,pow_ab3[7:0],val_ab2[22:0]} : {flag3,pow_ab3[7:0],val_ab2[22:0]};
 
endmodule 

/*
module test_add    //不同符号的浮点数据相加
(
	input wire MAIN_CLK,    
	input wire [31:0] a,
	input wire [31:0] b,
	
	output wire [31:0] ab
);
 
reg [7:0] pow_a;
reg [7:0] pow_b;
reg [22:0] val_a;
reg [22:0] val_b;
reg flag_a;
reg flag_b;
reg flag;
always @(*)
begin
	flag_a = a[31];   //提取符号
	flag_b= b[31];
	flag = flag_a^flag_b;
	pow_a = a[30:23];
	pow_b = b[30:23];
	val_a = a[22:0];
	val_b = b[22:0];
end
//比较指数大小提取指数差值
reg [24:0] val_max;
reg [24:0] val_min; 
reg [7:0] pow_diff;
reg [7:0] pow_ab1;
reg flag1;
always @(negedge MAIN_CLK )
begin
	if (flag ) begin 
		if(pow_a > pow_b)    
		begin
			flag1 <= flag_a;  //输出符号随a
			pow_ab1 <= pow_a;
			pow_diff <= pow_a - pow_b;
			val_max <= {2'b01,val_a};
			val_min <= {2'b01,val_b};
		end
	else if(pow_a < pow_b) 
		begin
			flag1 <= flag_b;  //输出符号随b
			pow_ab1 <= pow_b;
			pow_diff <= pow_b - pow_a;
			val_max <= {2'b01,val_b};
			val_min <= {2'b01,val_a};
		end
	else
		begin
			pow_ab1 <= pow_a;
			pow_diff <= 0;
			if(val_a > val_b)
				begin
					flag1 <= flag_a;  //输出符号随a
					val_max <= {2'b01,val_a};
					val_min <= {2'b01,val_b};
				end
			else //if(val_a < val_b)
				begin
					flag1 <= flag_b;  //输出符号随b
					val_max <= {2'b01,val_b};
					val_min <= {2'b01,val_a};
				end 
		end 
	end
	
	else begin
		flag1 <= flag_a;
	if(pow_a > pow_b)    
		begin
			pow_ab1 <= pow_a;
			pow_diff <= pow_a - pow_b;
			val_max <= {2'b01,val_a};
			val_min <= {2'b01,val_b};
		end
	else 
		begin
			pow_ab1 <= pow_b;
			pow_diff <= pow_b - pow_a;
			val_max <= {2'b01,val_b};
			val_min <= {2'b01,val_a};
		end
	
	end
	
end
//计数输出时的数值部分
reg [7:0] pow_ab2;
reg [24:0] val_ab1;
reg flag2;
always @(negedge MAIN_CLK )    //当输入的绝对值较大值是较小值的1万倍以上时，则直接输出较大者
begin
	flag2 <= flag1;
	pow_ab2 <= pow_ab1;
	if (flag) begin
	case(pow_diff)
		0: begin val_ab1 <= val_max - val_min; end
		1: begin val_ab1 <= val_max - {1'b0,val_min[24:1]}; end
		2: begin val_ab1 <= val_max - {2'b0,val_min[24:2]}; end
		3: begin val_ab1 <= val_max - {3'b0,val_min[24:3]}; end
		4: begin val_ab1 <= val_max - {4'b0,val_min[24:4]}; end
		5: begin val_ab1 <= val_max - {5'b0,val_min[24:5]}; end
		6: begin val_ab1 <= val_max - {6'b0,val_min[24:6]}; end
		7: begin val_ab1 <= val_max - {7'b0,val_min[24:7]}; end
		8: begin val_ab1 <= val_max - {8'b0,val_min[24:8]}; end
		9: begin val_ab1 <= val_max - {9'b0,val_min[24:9]}; end
		10: begin val_ab1 <= val_max - {10'b0,val_min[24:10]}; end
		11: begin val_ab1 <= val_max - {11'b0,val_min[24:11]}; end
		12: begin val_ab1 <= val_max - {12'b0,val_min[24:12]}; end
		13: begin val_ab1 <= val_max - {13'b0,val_min[24:13]}; end
		14: begin val_ab1 <= val_max - {14'b0,val_min[24:14]}; end
//		15: begin val_ab1 <= val_max - {15'b0,val_min[24:15]}; end
//		16: begin val_ab1 <= val_max - {16'b0,val_min[24:16]}; end
//		17: begin val_ab1 <= val_max - {17'b0,val_min[24:17]}; end
//		18: begin val_ab1 <= val_max - {18'b0,val_min[24:18]}; end
//		19: begin val_ab1 <= val_max - {19'b0,val_min[24:19]}; end
//		20: begin val_ab1 <= val_max - {20'b0,val_min[24:20]}; end
//		21: begin val_ab1 <= val_max - {21'b0,val_min[24:21]}; end
//		22: begin val_ab1 <= val_max - {22'b0,val_min[24:22]}; end
//		23: begin val_ab1 <= val_max - {23'b0,val_min[24:23]}; end
		default: begin val_ab1 <= val_max; end
	endcase 
	end
	else begin
	case(pow_diff)
		0: begin val_ab1 <= val_max + val_min; end
		1: begin val_ab1 <= val_max + {1'b0,val_min[24:1]}; end
		2: begin val_ab1 <= val_max + {2'b0,val_min[24:2]}; end
		3: begin val_ab1 <= val_max + {3'b0,val_min[24:3]}; end
		4: begin val_ab1 <= val_max + {4'b0,val_min[24:4]}; end
		5: begin val_ab1 <= val_max + {5'b0,val_min[24:5]}; end
		6: begin val_ab1 <= val_max + {6'b0,val_min[24:6]}; end
		7: begin val_ab1 <= val_max + {7'b0,val_min[24:7]}; end
		8: begin val_ab1 <= val_max + {8'b0,val_min[24:8]}; end
		9: begin val_ab1 <= val_max + {9'b0,val_min[24:9]}; end
		10: begin val_ab1 <= val_max + {10'b0,val_min[24:10]}; end
		11: begin val_ab1 <= val_max + {11'b0,val_min[24:11]}; end
		12: begin val_ab1 <= val_max + {12'b0,val_min[24:12]}; end
		13: begin val_ab1 <= val_max + {13'b0,val_min[24:13]}; end
		14: begin val_ab1 <= val_max + {14'b0,val_min[24:14]}; end
//		15: begin val_ab1 <= val_max + {15'b0,val_min[24:15]}; end
//		16: begin val_ab1 <= val_max + {16'b0,val_min[24:16]}; end
//		17: begin val_ab1 <= val_max + {17'b0,val_min[24:17]}; end
//		18: begin val_ab1 <= val_max + {18'b0,val_min[24:18]}; end
//		19: begin val_ab1 <= val_max + {19'b0,val_min[24:19]}; end
//		20: begin val_ab1 <= val_max + {20'b0,val_min[24:20]}; end
//		21: begin val_ab1 <= val_max + {21'b0,val_min[24:21]}; end
//		22: begin val_ab1 <= val_max + {22'b0,val_min[24:22]}; end
//		23: begin val_ab1 <= val_max + {23'b0,val_min[24:23]}; end
		default: begin val_ab1 <= val_max; end
	endcase 
	end
	
end 	 
//对最后的输出指数部分和数据部分进行校准
reg [8:0] pow_ab3;
reg [23:0] val_ab2;
reg flag3;
always @(negedge MAIN_CLK )
begin

	if (flag) begin 
	flag3 <= flag2;
	if(val_ab1[23] == 1)   //说明减法过程中数据没有借位
		begin
			pow_ab3 <= pow_ab2;
			val_ab2 <= val_ab1[23:0]; //得到最后输出的小数部分
		end
	else if(val_ab1[22] == 1)
		begin
			pow_ab3 <= pow_ab2 - 1;
			val_ab2 <= {val_ab1[22:0],1'b0}; //得到最后输出的小数部分			
		end
	else if(val_ab1[21] == 1)
		begin
			pow_ab3 <= pow_ab2 - 2;
			val_ab2 <= {val_ab1[21:0],2'b0}; //得到最后输出的小数部分			
		end
	else if(val_ab1[20] == 1)
		begin
			pow_ab3 <= pow_ab2 - 3;
			val_ab2 <= {val_ab1[20:0],3'b0}; //得到最后输出的小数部分			
		end
	else if(val_ab1[19] == 1)
		begin
			pow_ab3 <= pow_ab2 - 4;
			val_ab2 <= {val_ab1[19:0],4'b0}; //得到最后输出的小数部分			
		end
	else if(val_ab1[18] == 1)
		begin
			pow_ab3 <= pow_ab2 - 5;
			val_ab2 <= {val_ab1[18:0],5'b0}; //得到最后输出的小数部分			
		end
	else if(val_ab1[17] == 1)
		begin
			pow_ab3 <= pow_ab2 - 6;
			val_ab2 <= {val_ab1[17:0],6'b0}; //得到最后输出的小数部分			
		end
	else if(val_ab1[16] == 1)
		begin
			pow_ab3 <= pow_ab2 - 7;
			val_ab2 <= {val_ab1[16:0],7'b0}; //得到最后输出的小数部分			
		end
	else if(val_ab1[15] == 1)
		begin
			pow_ab3 <= pow_ab2 - 8;
			val_ab2 <= {val_ab1[15:0],8'b0}; //得到最后输出的小数部分			
		end
	else if(val_ab1[14] == 1)
		begin
			pow_ab3 <= pow_ab2 - 9;
			val_ab2 <= {val_ab1[14:0],9'b0}; //得到最后输出的小数部分			
		end
	else if(val_ab1[13] == 1)
		begin
			pow_ab3 <= pow_ab2 - 10;
			val_ab2 <= {val_ab1[13:0],10'b0}; //得到最后输出的小数部分			
		end
	else if(val_ab1[12] == 1)
		begin
			pow_ab3 <= pow_ab2 - 11;
			val_ab2 <= {val_ab1[12:0],11'b0}; //得到最后输出的小数部分			
		end
	else if(val_ab1[11] == 1)
		begin
			pow_ab3 <= pow_ab2 - 12;
			val_ab2 <= {val_ab1[11:0],12'b0}; //得到最后输出的小数部分			
		end
	else if(val_ab1[10] == 1)
		begin
			pow_ab3 <= pow_ab2 - 13;
			val_ab2 <= {val_ab1[10:0],13'b0}; //得到最后输出的小数部分			
		end		
	else
		begin
			pow_ab3 <= 0;
			val_ab2 <= 0;  
		end 
	end
	
	else begin
	flag3 <= flag2;
	if(val_ab1[24] == 1)   //说明加法过程中数据有溢出
		begin
			pow_ab3 <= pow_ab2 + 1;
			val_ab2 <= val_ab1[24:1]; //得到最后输出的小数部分
		end
	else
		begin
			pow_ab3 <= pow_ab2;
			val_ab2 <= val_ab1[23:0]; //得到最后输出的小数部分
		end 
	end
end
//对输出进行打包 
assign ab = flag ?(pow_ab3[8]==1)?{32'h0}:{flag3,pow_ab3[7:0],val_ab2[22:0]} : {flag3,pow_ab3[7:0],val_ab2[22:0]};
 
endmodule 
*/

add_tb.v
`timescale 1ns/1ps

module add_tb;
	reg clk;
	initial clk = 0;
	always #5 clk=~clk;
	
	reg [31:0] rnd1mem [0:999];
	reg [31:0] rnd2mem [0:999];
	reg [10:0] addr;
	wire [31:0] data_o;
	wire [31:0] a,b;
	//mul m1(clk,rnd1mem[addr],data);
	reg [3:0] clk_10;
	reg flag;

	
	initial begin
       $readmemh("E:/CASIA/SNN_RL-co/code_part/generate_mul_data/rnd1hex.txt",rnd1mem);
		 $readmemh("E:/CASIA/SNN_RL-co/code_part/generate_mul_data/rnd2hex.txt",rnd2mem);
       addr = 0;
		 clk_10 = 0;
		 flag = 0;
	end
	integer file1;
	initial begin
	file1 = $fopen("E:/CASIA/SNN_RL-co/code_part/generate_mul_data/add_result.txt","w");
	end
	always @(posedge clk ) begin
		$fwrite(file1,"%h\n",data_o);
		if (addr >= 999) begin
		$fclose(file1);
		$stop;
		end
		else  begin addr = addr + 1;
		
		end
	end
	
	initial
        begin            
            $dumpfile("add_tb.vcd");
            $dumpvars(0,add_tb);
        end


	/*always @(posedge clk) begin
		clk_10 <= clk_10 + 1;
		if (clk_10 == 8)
		flag <= 1;
		else if (clk_10 > 9) begin
		flag <= 0;
		clk_10 <= 0;
		end
		else 
		flag <= 0;
	end
*/
	assign a =rnd1mem[addr];
	assign b =rnd2mem[addr];
	add a1(.MAIN_CLK(clk),.a(a),.b(b),.ab(data_o));
endmodule

add_tb.vcd
$date
	Thu Aug 19 11:18:20 2021
$end
$version
	Icarus Verilog
$end
$timescale
	1ps
$end
$scope module add_tb $end
$var wire 32 ! a [31:0] $end
$var wire 32 " b [31:0] $end
$var wire 32 # data_o [31:0] $end
$var reg 11 $ addr [10:0] $end
$var reg 1 % clk $end
$var reg 4 & clk_10 [3:0] $end
$var reg 1 ' flag $end
$var integer 32 ( file1 [31:0] $end
$scope module a1 $end
$var wire 1 % MAIN_CLK $end
$var wire 32 ) a [31:0] $end
$var wire 32 * b [31:0] $end
$var wire 32 + ab [31:0] $end
$var reg 1 , flag $end
$var reg 1 - flag1 $end
$var reg 1 . flag2 $end
$var reg 1 / flag3 $end
$var reg 1 0 flag_a $end
$var reg 1 1 flag_b $end
$var reg 8 2 pow_a [7:0] $end
$var reg 8 3 pow_ab1 [7:0] $end
$var reg 8 4 pow_ab2 [7:0] $end
$var reg 9 5 pow_ab3 [8:0] $end
$var reg 8 6 pow_b [7:0] $end
$var reg 8 7 pow_diff [7:0] $end
$var reg 23 8 val_a [22:0] $end
$var reg 25 9 val_ab1 [24:0] $end
$var reg 24 : val_ab2 [23:0] $end
$var reg 23 ; val_b [22:0] $end
$var reg 25 < val_max [24:0] $end
$var reg 25 = val_min [24:0] $end
$upscope $end
$upscope $end
$enddefinitions $end
#0
$dumpvars
b100000011110110111000011 =
b100100100110001111011100 <
b11110110111000011 ;
b100000111011000011001000 :
b100000111011000011001 9
b100100110001111011100 8
b0 7
b10000010 6
b1111111 5
b10000010 4
b10000010 3
b10000010 2
11
00
0/
0.
0-
1,
b111111100000111011000011001000 +
b11000001000000011110110111000011 *
b1000001000100100110001111011100 )
b10000000000000000000000000000011 (
0'
b0 &
0%
b0 $
b111111100000111011000011001000 #
b11000001000000011110110111000011 "
b1000001000100100110001111011100 !
$end
#5000
b1000001100000000110001110011100 #
b1000001100000000110001110011100 +
b100000000110001110011100 :
b10000011 5
b1000000001100011100111000 9
b111100011011000000111010 =
b100001111110111100011011 <
b1 7
b11100011011000000111010 ;
b1111110111100011011 8
b10000001 6
0,
01
b1000001000001111110111100011011 !
b1000001000001111110111100011011 )
b1000000111100011011000000111010 "
b1000000111100011011000000111010 *
b1 $
1%
#10000
0%
#15000
b11000000001110111101111100101000 #
b11000000001110111101111100101000 +
b101110111101111100101000 :
b10000000 5
1/
b10111011110111110010100 9
b10000001 4
1.
b100100000110100001101010 =
b111011100101011111111110 <
1-
b0 7
b10000001 3
b11011100101011111111110 ;
b100000110100001101010 8
b10000001 2
1,
11
b1000000100100000110100001101010 !
b1000000100100000110100001101010 )
b11000000111011100101011111111110 "
b11000000111011100101011111111110 *
b10 $
1%
#20000
0%
#25000
b111111101010111010001000111000 #
b111111101010111010001000111000 +
b101010111010001000111000 :
b1111111 5
0/
b101010111010001000111 9
b10000010 4
0.
b100001011111101101001101 =
b100110110110111110010100 <
0-
b10000010 3
b110110110111110010100 ;
b1011111101101001101 8
b10000010 6
b10000010 2
01
10
b11000001000001011111101101001101 !
b11000001000001011111101101001101 )
b1000001000110110110111110010100 "
b1000001000110110110111110010100 *
b11 $
1%
#30000
0%
#35000
b11000000101100001111101001010101 #
b11000000101100001111101001010101 +
b101100001111101001010101 :
b10000001 5
1/
b1011000011111010010101010 9
b10000000 4
1.
b101011111011100100111101 =
b101100100011101101101101 <
b10000000 3
1-
b1100100011101101101101 ;
b1011111011100100111101 8
b10000000 6
b10000000 2
0,
11
b11000000001011111011100100111101 !
b11000000001011111011100100111101 )
b11000000001100100011101101101101 "
b11000000001100100011101101101101 *
b100 $
1%
#40000
0%
#45000
b11000000110010110000101100101111 #
b11000000110010110000101100101111 +
b110010110000101100101111 :
b110010110000101100101111 9
b10000001 4
b100011101001111010000000 =
b100000111011101111101111 <
b1 7
b10000001 3
b11101001111010000000 ;
b111011101111101111 8
b10000001 2
b11000000100000111011101111101111 !
b11000000100000111011101111101111 )
b11000000000011101001111010000000 "
b11000000000011101001111010000000 *
b101 $
1%
#50000
0%
#55000
b11000001100000010101111000110011 #
b11000001100000010101111000110011 +
b100000010101111000110011 :
b10000011 5
b1000000101011110001100111 9
b10000010 4
b111011010100110101100110 =
b100011000001010110110100 <
b10000010 3
b11011010100110101100110 ;
b11000001010110110100 8
b10000001 6
b10000010 2
b11000001000011000001010110110100 !
b11000001000011000001010110110100 )
b11000000111011010100110101100110 "
b11000000111011010100110101100110 *
b110 $
1%
#60000
0%
#65000
b10111111011000001011011000000000 #
b10111111011000001011011000000000 +
b111000001011011000000000 :
b1111110 5
b111000001011011000000 9
b10000001 4
b111010010000011001101100 =
b100100001001100111110110 <
b10000001 3
b11010010000011001101100 ;
b100001001100111110110 8
b10000000 6
b10000001 2
1,
01
b11000000100100001001100111110110 !
b11000000100100001001100111110110 )
b1000000011010010000011001101100 "
b1000000011010010000011001101100 *
b111 $
1%
#70000
0%
#75000
b1000001001100100001110101000110 #
b1000001001100100001110101000110 +
b101100100001110101000110 :
b10000010 5
0/
b101100100001110101000110 9
b10000010 4
0.
b101110101001000110000110 =
b100110101100101100010110 <
b11 7
b10000010 3
0-
b1110101001000110000110 ;
b110101100101100010110 8
b1111111 6
b10000010 2
0,
00
b1000001000110101100101100010110 !
b1000001000110101100101100010110 )
b111111101110101001000110000110 "
b111111101110101001000110000110 *
b1000 $
1%
#80000
0%
#85000
b11000000110101110011110011010010 #
b11000000110101110011110011010010 +
b110101110011110011010010 :
b10000001 5
1/
b11010111001111001101001 9
1.
b101101111000101000101011 =
b100000101000111110101110 <
1-
b1101111000101000101011 ;
b101000111110101110 8
1,
10
b11000001000000101000111110101110 !
b11000001000000101000111110101110 )
b111111101101111000101000101011 "
b111111101101111000101000101011 *
b1001 $
1%
#90000
0%
#95000
b11000001100001101111111101100101 #
b11000001100001101111111101100101 +
b100001101111111101100101 :
b10000011 5
b1000011011111111011001011 9
b111110101111100110110101 =
b100100001000000111110001 <
b1 7
b11110101111100110110101 ;
b100001000000111110001 8
b10000001 6
0,
11
b11000001000100001000000111110001 !
b11000001000100001000000111110001 )
b11000000111110101111100110110101 "
b11000000111110101111100110110101 *
b1010 $
1%
#100000
0%
#105000
b1000001000100011100100100110100 #
b1000001000100011100100100110100 +
b100100011100100100110100 :
b10000010 5
0/
b1001000111001001001101000 9
b10000001 4
0.
b110000001000111110000110 =
b111100110110111010000111 <
b10 7
b10000001 3
0-
b10000001000111110000110 ;
b11100110110111010000111 8
b1111111 6
b10000001 2
01
00
b1000000111100110110111010000111 !
b1000000111100110110111010000111 )
b111111110000001000111110000110 "
b111111110000001000111110000110 *
b1011 $
1%
#110000
0%
#115000
b1000000101011110011101110101000 #
b1000000101011110011101110101000 +
b101011110011101110101000 :
b10000001 5
b10101111001110111010100 9
b10000010 4
b101100100001000101011110 =
b100001000010001000101011 <
b10000010 3
b1000010001000101011 ;
b1100100001000101011110 8
b10000010 6
b10000000 2
1,
10
b11000000001100100001000101011110 !
b11000000001100100001000101011110 )
b1000001000001000010001000101011 "
b1000001000001000010001000101011 *
b1100 $
1%
#120000
0%
#125000
b1000001100110101000101000011011 #
b1000001100110101000101000011011 +
b100110101000101000011011 :
b10000011 5
b1001101010001010000110110 9
b100110001001111111111010 =
b100111000111010000111100 <
b0 7
b111000111010000111100 ;
b110001001111111111010 8
b10000010 2
0,
00
b1000001000110001001111111111010 !
b1000001000110001001111111111010 )
b1000001000111000111010000111100 "
b1000001000111000111010000111100 *
b1101 $
1%
#130000
0%
#135000
b10111101000001010000001100000000 #
b10111101000001010000001100000000 +
b100001010000001100000000 :
b1111010 5
1/
b1000010100000011 9
1.
b100101111100001011011101 =
b100110000100011111100000 <
1-
b101111100001011011101 ;
b110000100011111100000 8
1,
10
b11000001000110000100011111100000 !
b11000001000110000100011111100000 )
b1000001000101111100001011011101 "
b1000001000101111100001011011101 *
b1110 $
1%
#140000
0%
#145000
b111110100101001001110000110000 #
b111110100101001001110000110000 +
b100101001001110000110000 :
b1111101 5
0/
b10010100100111000011 9
b10000001 4
0.
b111100001100010100100000 =
b111110100000111011100011 <
0-
b10000001 3
b11100001100010100100000 ;
b11110100000111011100011 8
b10000001 6
b10000001 2
11
00
b1000000111110100000111011100011 !
b1000000111110100000111011100011 )
b11000000111100001100010100100000 "
b11000000111100001100010100100000 *
b1111 $
1%
#150000
0%
#155000
b10111110000001010011001000100000 #
b10111110000001010011001000100000 +
b100001010011001000100000 :
b1111100 5
1/
b1000010100110010001 9
1.
b100101000101011101100000 =
b100110001000000011110001 <
1-
b101000101011101100000 ;
b110001000000011110001 8
01
10
b11000000100110001000000011110001 !
b11000000100110001000000011110001 )
b1000000100101000101011101100000 "
b1000000100101000101011101100000 *
b10000 $
1%
#160000
0%
#165000
b10111111110000111101001111111000 #
b10111111110000111101001111111000 +
b110000111101001111111000 :
b1111111 5
b1100001111010011111110 9
b101111001111000011000111 =
b111011011110010111000101 <
b1111001111000011000111 ;
b11011011110010111000101 8
b11000000111011011110010111000101 !
b11000000111011011110010111000101 )
b1000000101111001111000011000111 "
b1000000101111001111000011000111 *
b10001 $
1%
#170000
0%
#175000
b11000000100110111100101100110101 #
b11000000100110111100101100110101 +
b100110111100101100110101 :
b10000001 5
b100110111100101100110101 9
b101110110100010100001111 =
b110010101001110001111000 <
b10 7
b10010101001110001111000 ;
b1110110100010100001111 8
b1111111 2
11
00
b111111101110110100010100001111 !
b111111101110110100010100001111 )
b11000000110010101001110001111000 "
b11000000110010101001110001111000 *
b10010 $
1%
#180000
0%
#185000
b1000000100100011001100000010001 #
b1000000100100011001100000010001 +
b100100011001100000010001 :
0/
b1001000110011000000100011 9
b10000000 4
0.
b110011100001101111001010 =
b101111000010001000111110 <
b1 7
b10000000 3
0-
b1111000010001000111110 ;
b10011100001101111001010 8
b10000000 6
0,
01
b111111110011100001101111001010 !
b111111110011100001101111001010 )
b1000000001111000010001000111110 "
b1000000001111000010001000111110 *
b10011 $
1%
#190000
0%
#195000
b11000000111101000010101110100010 #
b11000000111101000010101110100010 +
b111101000010101110100010 :
1/
b11110100001010111010001 9
b10000010 4
1.
b100010100000000101011000 =
b100010110101010111111100 <
b11 7
b10000010 3
1-
b10100000000101011000 ;
b10110101010111111100 8
b1111111 6
b10000010 2
1,
10
b11000001000010110101010111111100 !
b11000001000010110101010111111100 )
b111111100010100000000101011000 "
b111111100010100000000101011000 *
b10100 $
1%
#200000
0%
